sqlhandler/__init__.py
sqlhandler/enums.py
sqlhandler/sql.py
sqlhandler/custom/__init__.py
sqlhandler/custom/expression.py
sqlhandler/custom/field.py
sqlhandler/custom/misc.py
sqlhandler/custom/model.py
sqlhandler/custom/query.py
sqlhandler/custom/relationship.py
sqlhandler/custom/table.py
sqlhandler/database/__init__.py
sqlhandler/database/database.py
sqlhandler/database/meta.py
sqlhandler/database/name.py
sqlhandler/database/schema.py
sqlhandler/database/shape.py
sqlhandler/django/__init__.py
sqlhandler/django/config.py
sqlhandler/django/database.py
sqlhandler/django/model.py
sqlhandler/django/sql.py
sqlhandler/utils/__init__.py
sqlhandler/utils/config.py
sqlhandler/utils/log.py
sqlhandler/utils/utils.py
sqlhandler-0.3.14.dist-info/LICENSE
sqlhandler-0.3.14.dist-info/METADATA
sqlhandler-0.3.14.dist-info/WHEEL
sqlhandler-0.3.14.dist-info/top_level.txt
sqlhandler-0.3.14.dist-info/RECORD
