Metadata-Version: 2.1
Name: sqlhandler
Version: 0.3.14
Summary: Sql handler class controlling sqlalchemy resources and granting access to sqlalchemy object subclasses with additional convenience methods.
Home-page: https://github.com/matthewgdv/sqlhandler
Author: Matt GdV
Author-email: matthewgdv@gmail.com
License: MIT
Platform: UNKNOWN
Classifier: Development Status :: 3 - Alpha
Classifier: Intended Audience :: Developers
Classifier: Programming Language :: Python :: 3.8
Requires-Dist: django
Requires-Dist: alembic
Requires-Dist: maybe-else
Requires-Dist: numpy
Requires-Dist: pandas
Requires-Dist: pathmagic
Requires-Dist: pymiscutils
Requires-Dist: pysubtypes
Requires-Dist: sqlalchemy
Requires-Dist: sqlparse
